googlepycraft/__init__.py
googlepycraft/app_config.py
googlepycraft/begin.py
googlepycraft/fireStore/__init__.py
googlepycraft/fireStore/firestoreupload.py
googlepycraft/googleSheet/__init__.py
googlepycraft/googleSheet/gsheetsdb.py
googlepycraft-1.0.0.dist-info/METADATA
googlepycraft-1.0.0.dist-info/WHEEL
googlepycraft-1.0.0.dist-info/top_level.txt
googlepycraft-1.0.0.dist-info/RECORD
